junk/__init__.py
junk/cleanup.py
junk/cli.py
junk_remover_cli-0.1.3.dist-info/METADATA
junk_remover_cli-0.1.3.dist-info/WHEEL
junk_remover_cli-0.1.3.dist-info/entry_points.txt
junk_remover_cli-0.1.3.dist-info/licenses/LICENSE
junk_remover_cli-0.1.3.dist-info/RECORD
