Metadata-Version: 2.4
Name: junk-remover-cli
Version: 0.1.3
Summary: Universal cleanup executor - Automated deletion of unwanted files and directories
Project-URL: Homepage, https://github.com/AuraCulture/Junk
Project-URL: Bug Reports, https://github.com/AuraCulture/Junk/issues
Project-URL: Source, https://github.com/AuraCulture/Junk
Project-URL: Documentation, https://github.com/AuraCulture/Junk#readme
Author-email: Junk CLI <maintainer@junk-cli.dev>
License: MIT License
License-File: LICENSE
Keywords: automation,cleanup,cli,delete,devtools,files,junk,universal
Classifier: Development Status :: 4 - Beta
Classifier: Environment :: Console
Classifier: Intended Audience :: Developers
Classifier: License :: OSI Approved :: MIT License
Classifier: Operating System :: OS Independent
Classifier: Programming Language :: Python :: 3
Classifier: Programming Language :: Python :: 3.7
Classifier: Programming Language :: Python :: 3.8
Classifier: Programming Language :: Python :: 3.9
Classifier: Programming Language :: Python :: 3.10
Classifier: Programming Language :: Python :: 3.11
Classifier: Programming Language :: Python :: 3.12
Classifier: Topic :: Software Development :: Build Tools
Classifier: Topic :: System :: Filesystems
Classifier: Topic :: System :: Systems Administration
Classifier: Topic :: Utilities
Requires-Python: >=3.7
